nonemptystr/__init__.py
nonemptystr/exceptions.py
nonemptystr/nonemptystr.py
nonemptystr/py.typed
nonemptystr-1.0.0.dist-info/LICENSE
nonemptystr-1.0.0.dist-info/METADATA
nonemptystr-1.0.0.dist-info/WHEEL
nonemptystr-1.0.0.dist-info/RECORD
