Metadata-Version: 2.1
Name: nonemptystr
Version: 1.0.0
Summary: Non-empty string
Home-page: https://github.com/nekonoshiri/nonemptystr
License: MIT
Keywords: str
Author: Shiri Nekono
Author-email: gexira.halen.toms@gmail.com
Maintainer: Shiri Nekono
Maintainer-email: gexira.halen.toms@gmail.com
Requires-Python: >=3.8.1
Classifier: Development Status :: 5 - Production/Stable
Classifier: Intended Audience :: Developers
Classifier: License :: OSI Approved :: MIT License
Classifier: Programming Language :: Python :: 3
Classifier: Programming Language :: Python :: 3.9
Classifier: Programming Language :: Python :: 3.10
Classifier: Programming Language :: Python :: 3.11
Classifier: Programming Language :: Python :: 3.12
Classifier: Topic :: Software Development :: Libraries
Classifier: Topic :: Utilities
Project-URL: Documentation, https://github.com/nekonoshiri/nonemptystr
Project-URL: Repository, https://github.com/nekonoshiri/nonemptystr
